agentic_radar/__init__.py
agentic_radar/__main__.py
agentic_radar/analysis/__init__.py
agentic_radar/analysis/analyze.py
agentic_radar/analysis/ast_utils.py
agentic_radar/analysis/autogen/__init__.py
agentic_radar/analysis/autogen/agentchat/__init__.py
agentic_radar/analysis/autogen/agentchat/analyze.py
agentic_radar/analysis/autogen/agentchat/graph.py
agentic_radar/analysis/autogen/agentchat/mcp.py
agentic_radar/analysis/autogen/agentchat/models.py
agentic_radar/analysis/autogen/agentchat/parse.py
agentic_radar/analysis/crewai/__init__.py
agentic_radar/analysis/crewai/analyze.py
agentic_radar/analysis/crewai/crew_process.py
agentic_radar/analysis/crewai/graph_converter.py
agentic_radar/analysis/crewai/models/__init__.py
agentic_radar/analysis/crewai/models/agent.py
agentic_radar/analysis/crewai/models/graph.py
agentic_radar/analysis/crewai/models/mcp.py
agentic_radar/analysis/crewai/models/tool.py
agentic_radar/analysis/crewai/parsing/__init__.py
agentic_radar/analysis/crewai/parsing/agents.py
agentic_radar/analysis/crewai/parsing/crews.py
agentic_radar/analysis/crewai/parsing/custom_tools.py
agentic_radar/analysis/crewai/parsing/mcp.py
agentic_radar/analysis/crewai/parsing/predefined_tools.py
agentic_radar/analysis/crewai/parsing/tasks.py
agentic_radar/analysis/crewai/parsing/utils.py
agentic_radar/analysis/crewai/parsing/yaml_config.py
agentic_radar/analysis/crewai/prompt.py
agentic_radar/analysis/crewai/tool_categories.json
agentic_radar/analysis/crewai/tool_categorizer.py
agentic_radar/analysis/crewai/tool_descriptions.py
agentic_radar/analysis/langgraph/__init__.py
agentic_radar/analysis/langgraph/agent_tracking.py
agentic_radar/analysis/langgraph/analyze.py
agentic_radar/analysis/langgraph/custom_tools.py
agentic_radar/analysis/langgraph/graph.py
agentic_radar/analysis/langgraph/mcp.py
agentic_radar/analysis/langgraph/models.py
agentic_radar/analysis/langgraph/predefined_tools.json
agentic_radar/analysis/langgraph/predefined_tools.py
agentic_radar-0.14.0.dist-info/LICENSE
agentic_radar-0.14.0.dist-info/METADATA
agentic_radar-0.14.0.dist-info/WHEEL
agentic_radar-0.14.0.dist-info/entry_points.txt
agentic_radar-0.14.0.dist-info/RECORD
