Metadata-Version: 2.3
Name: agentic-radar
Version: 0.14.0
Summary: A python library for generating reports for agentic systems.
License: Apache License
Author: SPLX
Author-email: developers@splx.ai
Maintainer: SPLX
Maintainer-email: developers@splx.ai
Requires-Python: >=3.9
Classifier: Development Status :: 3 - Alpha
Classifier: License :: OSI Approved :: Apache Software License
Classifier: Programming Language :: Python :: 3
Classifier: Programming Language :: Python :: 3.9
Provides-Extra: crewai
Provides-Extra: openai-agents
Requires-Dist: crewai-tools (>=0.38.1) ; (python_version >= "3.10" and python_version < "3.13") and (extra == "crewai")
Requires-Dist: dotenv (>=0.9.9,<0.10.0)
Requires-Dist: importlib-resources (>=6.5.2,<7.0.0)
Requires-Dist: jinja2 (>=3.1.5,<4.0.0)
Requires-Dist: openai (>=1.73.0,<2.0.0)
Requires-Dist: openai-agents (>=0.0.13,<0.0.14) ; extra == "openai-agents"
Requires-Dist: pydantic (>=2.10.6)
Requires-Dist: pyyaml (>=6.0.2,<7.0.0)
Requires-Dist: rich (>=13.7.0,<14.0.0)
Requires-Dist: typer-slim (>=0.15.1)
Project-URL: Homepage, https://github.com/splx-ai/agentic-radar
Project-URL: Source, https://github.com/splx-ai/agentic-radar
Project-URL: Tracker, https://github.com/splx-ai/agentic-radar/issues
